setup.py
burrahobbit/__init__.py
burrahobbit/_tree.py
burrahobbit/treedict.py
burrahobbit/treeset.py
burrahobbit.egg-info/PKG-INFO
burrahobbit.egg-info/SOURCES.txt
burrahobbit.egg-info/dependency_links.txt
burrahobbit.egg-info/top_level.txt
burrahobbit.egg-info/zip-safe
burrahobbit/test/__init__.py
burrahobbit/test/test_dict.py
burrahobbit/test/test_set.py
burrahobbit/test/test_tree.py