Metadata-Version: 1.0
Name: burrahobbit
Version: 0.1.0
Summary: Persistent data-structures in Python.
Home-page: https://github.com/segfaulthunter/burrahobbit
Author: Florian Mayer
Author-email: florian.mayer@bitsrc.org
License: MIT
Keywords: persistent datastructures
Platform: UNKNOWN
